{
  "schemaVersion": "1.0.0",
  "packages": [
    {
      "name": "ember-cli",
      "version": "3.14.0",
      "blueprints": [
        {
          "name": "app",
          "outputRepo": "https://github.com/ember-cli/ember-new-output",
          "codemodsSource": "ember-app-codemods-manifest@1",
          "isBaseBlueprint": true,
          "options": [
            "--yarn",
            "--no-welcome"
          ]
        }
      ]
    },
    {
      "name": "@kellyselden/ember-blueprint",
      "version": "1.2.0",
      "blueprints": [
        {
          "name": "@kellyselden/ember-blueprint",
          "options": [
            "--repo-slug=ember-vr/ember-vr-shopping"
          ]
        }
      ]
    },
    {
      "name": "ember-cli-mirage",
      "version": "1.1.8",
      "blueprints": [
        {
          "name": "ember-cli-mirage"
        }
      ]
    }
  ]
}
